[
    {
        "ID": "834126013010109",
        "fileName": "834126013010109.wav",
        "Start": "2022-04-01T19:14:05.199-05:00",
        "End": "2022-04-01T19:14:24.363-05:00",
        "callDirection": "Inbound",
        "callId": "00001013941648858443",
        "WhoCall": "923470369",
        "extension": "2193",
        "agenteId": "4737",
        "agentName": "BELEN CARRENO M",
        "duration": "20729"
    },
    {
        "ID": "834126013010111",
        "fileName": "834126013010111.wav",
        "Start": "2022-04-01T19:14:06.168-05:00",
        "End": "2022-04-01T19:15:10.380-05:00",
        "callDirection": "Inbound",
        "callId": "00001012021648858356",
        "WhoCall": "986780341",
        "extension": "1029",
        "agenteId": "4071",
        "agentName": "MILAGROS GARCIA S",
        "duration": "66425"
    },
    {
        "ID": "834126013010110",
        "fileName": "834126013010110.wav",
        "Start": "2022-04-01T19:14:05.665-05:00",
        "End": "2022-04-01T19:15:12.101-05:00",
        "callDirection": "Inbound",
        "callId": "00001013761648858434",
        "WhoCall": "937341676",
        "extension": "1003",
        "agenteId": "4068",
        "agentName": "MIGUEL GARCIA R",
        "duration": "67423"
    },
    {
        "ID": "834126013010115",
        "fileName": "834126013010115.wav",
        "Start": "2022-04-01T19:14:15.192-05:00",
        "End": "2022-04-01T19:15:18.540-05:00",
        "callDirection": "Inbound",
        "callId": "00001013931648858443",
        "WhoCall": "997921954",
        "extension": "2167",
        "agenteId": "2786",
        "agentName": "MATIAS NARVAEZ M",
        "duration": "64060"
    },
    {
        "ID": "834126013010108",
        "fileName": "834126013010108.wav",
        "Start": "2022-04-01T19:14:02.845-05:00",
        "End": "2022-04-01T19:15:47.943-05:00",
        "callDirection": "Inbound",
        "callId": "00001013791648858436",
        "WhoCall": "969415555",
        "extension": "2158",
        "agenteId": "2794",
        "agentName": "MARIANGEL CRUZADO C",
        "duration": "105989"
    },
    {
        "ID": "834126013010112",
        "fileName": "834126013010112.wav",
        "Start": "2022-04-01T19:14:07.774-05:00",
        "End": "2022-04-01T19:16:08.561-05:00",
        "callDirection": "Inbound",
        "callId": "00001013891648858441",
        "WhoCall": "947075792",
        "extension": "2180",
        "agenteId": "4633",
        "agentName": "EFRAIN MALLCCO C",
        "duration": "121819"
    },
    {
        "ID": "834126013010107",
        "fileName": "834126013010107.wav",
        "Start": "2022-04-01T19:14:02.542-05:00",
        "End": "2022-04-01T19:17:33.922-05:00",
        "callDirection": "Inbound",
        "callId": "00001013851648858440",
        "WhoCall": "956169724",
        "extension": "2048",
        "agenteId": "2842",
        "agentName": "PIERO ACEVEDO V",
        "duration": "212325"
    },
    {
        "ID": "834126013010114",
        "fileName": "834126013010114.wav",
        "Start": "2022-04-01T19:14:14.528-05:00",
        "End": "2022-04-01T19:17:59.224-05:00",
        "callDirection": "Inbound",
        "callId": "00001013871648858441",
        "WhoCall": "992155379",
        "extension": "1070",
        "agenteId": "2645",
        "agentName": "MAYRA CORDOVA R",
        "duration": "225618"
    },
    {
        "ID": "834126013010113",
        "fileName": "834126013010113.wav",
        "Start": "2022-04-01T19:14:12.184-05:00",
        "End": "2022-04-01T19:18:44.082-05:00",
        "callDirection": "Inbound",
        "callId": "00001013921648858442",
        "WhoCall": "913445490",
        "extension": "2070",
        "agenteId": "2647",
        "agentName": "MILAGROS GUTIERREZ C",
        "duration": "272613"
    }
]